{"cameraMode":{"drawMode":0,"name":"Shaded","section":"Shading Mode"},"sceneLighting":true,"audioPlay":false,"sceneViewState":{"m_AlwaysRefresh":false,"showFog":true,"showSkybox":true,"showFlares":true,"showImageEffects":true,"showParticleSystems":true,"showVisualEffectGraphs":true,"m_FxEnabled":true},"in2DMode":false,"pivot":{"x":-0.19000756740570069,"y":0.6918938159942627,"z":1.244969367980957},"rotation":{"x":-0.15934576094150544,"y":0.0828215628862381,"z":-0.013416669331490994,"w":-0.9836514592170715},"size":5.534379959106445,"orthographic":false}